AUTHORS.txt
CHANGES.rst
LICENSE.txt
MANIFEST.in
README.rst
setup.py
django_pandora.egg-info/PKG-INFO
django_pandora.egg-info/SOURCES.txt
django_pandora.egg-info/dependency_links.txt
django_pandora.egg-info/requires.txt
django_pandora.egg-info/top_level.txt
pandora/__init__.py
pandora/middleware.py
pandora/models.py