Metadata-Version: 1.0
Name: django-pandora
Version: 0.1.0
Summary: Opening Pandora's box by making django's request object available in a thread local.
Home-page: https://github.com/gregmuellegger/django-pandora
Author: Gregor Müllegger
Author-email: gregor@muellegger.de
License: BSD
Platform: UNKNOWN
Classifier: Development Status :: 4 - Beta
Classifier: Environment :: Web Environment
Classifier: Framework :: Django
Classifier: Intended Audience :: Developers
Classifier: License :: OSI Approved :: BSD License
Classifier: Natural Language :: English
Classifier: Operating System :: OS Independent
Classifier: Programming Language :: Python
